{
    "name": "Türkçe",
    "common": {
        "close": "Kapat",
        "cancel": "İptal et",
        "delete": "Sil",
        "download": "İndir",
        "loading": "Yükleniyor…",
        "remove": "Kaldır",
        "avatar": "Avatar",
        "okay": "Tamam",
        "nevermind": "Vazgeç",
        "language": "Dil",
        "new": "Yeni",
        "dismiss": "Kapat",
        "disconnect": "Kaldır",
        "connect": "Bağla",
        "profile": "Profil",
        "save": "Kaydet",
        "manage": "Yönet",
        "logout": "Oturumu Kapat"
    },
    "format_sections": {
        "mt": "Çoklu Parça",
        "stsm": "Tek Parça Akıllı Mix"
    },
    "format_buttons": {
        "audacity": "Audacity Projesi",
        "adobe_audition": "Adobe Audition Dosyası",
        "srt": "SubRip Metin",
        "plain_text": "Düz Metin"
    },
    "footer": {
        "tos": "Hizmet Şartları",
        "privacy": "Güvenlik Politikası"
    },
    "errors": {
        "invalid_format": "Geçersiz bir format sağlandı.",
        "invalid_body": "Sunucuya geçersiz bir istek gönderdik, muhtemelen bunu görmemelisiniz. Bu sorun devam ederse sayfayı yeniden yükleyin.",
        "unknown": "Bilinmeyen bir hata oluştu, daha sonra tekrar dene.",
        "server_error": "Bir sunucu hatası oluştu, daha sonra tekrar dene."
    },
    "login_page": {
        "header": "Craig paneline erişmek için Discord ile giriş yapın.",
        "disclaimer": "Oturumunuz açık tutmak için çerez kullanıyoruz. Oturum açarak, bize çerez barındırmak ve kullanmak için yetki veriyorsunuz.",
        "login": "Discord ile Giriş Yap"
    },
    "headers": {
        "supporter_status": "Destekçi Durumu",
        "cloud_backup": "Bulut Yedekleme"
    },
    "supporter_tiers": {
        "0": "Destekçi Değil",
        "10": "1. Kademe Destekçi",
        "20": "2. Kademe Destekçi",
        "30": "3. Kademe Destekçi",
        "100": "MP3 Tanrısı"
    },
    "supporter_status": {
        "dev_tier": "Bir geliştirici size bu kademeyi verdi!",
        "manage": "Aboneliği yönet",
        "cta": "Bir Destekçi Ol!"
    }
}
